{
  "created_at": "2026-04-01T21:54:25.144453Z",
  "doc_id": "F33095484.clean",
  "source_path": "../../data/ocr/_clean_md_improved/reliable/F33095484.clean.md",
  "config": {
    "min_words_soft": 12,
    "max_words_soft": 400,
    "low_alpha_threshold": 0.55,
    "high_digit_threshold": 0.35,
    "select_threshold": 0.5,
    "select_top_k": 60
  },
  "feedback": [
    {
      "para_id": "feedback",
      "text": "The contribution of the Central European Lawyers Initiative (CELI) is provided in the attached document.",
      "chunk_quality": "ok"
    }
  ],
  "sections": [
    {
      "section_id": "s0",
      "level": 0,
      "title": "__root__",
      "path": [],
      "ordinal": 0
    },
    {
      "section_id": "s1",
      "level": 1,
      "title": "Feedback – Digital Fairness Act",
      "path": [
        "Feedback – Digital Fairness Act"
      ],
      "ordinal": 1
    },
    {
      "section_id": "s2",
      "level": 2,
      "title": "About us",
      "path": [
        "Feedback – Digital Fairness Act",
        "About us"
      ],
      "ordinal": 2
    },
    {
      "section_id": "s3",
      "level": 2,
      "title": "The scope of the feedback",
      "path": [
        "Feedback – Digital Fairness Act",
        "The scope of the feedback"
      ],
      "ordinal": 3
    },
    {
      "section_id": "s4",
      "level": 2,
      "title": "Summary",
      "path": [
        "Feedback – Digital Fairness Act",
        "Summary"
      ],
      "ordinal": 4
    },
    {
      "section_id": "s5",
      "level": 2,
      "title": "More legislation is not always the answer",
      "path": [
        "Feedback – Digital Fairness Act",
        "More legislation is not always the answer"
      ],
      "ordinal": 5
    },
    {
      "section_id": "s6",
      "level": 2,
      "title": "General comments on the highlighted areas in the consultation",
      "path": [
        "Feedback – Digital Fairness Act",
        "General comments on the highlighted areas in the consultation"
      ],
      "ordinal": 6
    },
    {
      "section_id": "s7",
      "level": 2,
      "title": "Promote and support self-regulation",
      "path": [
        "Feedback – Digital Fairness Act",
        "Promote and support self-regulation"
      ],
      "ordinal": 7
    },
    {
      "section_id": "s8",
      "level": 2,
      "title": "When additional legislation may be warranted",
      "path": [
        "Feedback – Digital Fairness Act",
        "When additional legislation may be warranted"
      ],
      "ordinal": 8
    },
    {
      "section_id": "s9",
      "level": 1,
      "title": "Utilize existing rules",
      "path": [
        "Utilize existing rules"
      ],
      "ordinal": 9
    },
    {
      "section_id": "s10",
      "level": 1,
      "title": "Simplifications and the need to avoid overlapping and fragmented rules",
      "path": [
        "Simplifications and the need to avoid overlapping and fragmented rules"
      ],
      "ordinal": 10
    },
    {
      "section_id": "s11",
      "level": 1,
      "title": "Requirements must align with the needs of the average consumer",
      "path": [
        "Requirements must align with the needs of the average consumer"
      ],
      "ordinal": 11
    },
    {
      "section_id": "s12",
      "level": 2,
      "title": "Legislation must not be more burdensome than necessary",
      "path": [
        "Requirements must align with the needs of the average consumer",
        "Legislation must not be more burdensome than necessary"
      ],
      "ordinal": 12
    },
    {
      "section_id": "s13",
      "level": 1,
      "title": "A final comment on the consultation",
      "path": [
        "A final comment on the consultation"
      ],
      "ordinal": 13
    }
  ],
  "paragraphs": [
    {
      "para_id": "p0",
      "section_id": "s0",
      "section_path": [],
      "ordinal": 0,
      "text": "Sveriges Annonsörer Ref. Ares(2025)9114142 - 24/10/2025",
      "char_len": 55,
      "chunk_word_count": 10,
      "ratios": {
        "alpha": 0.5,
        "digit": 0.38,
        "non_space": 0.9090909090909091
      },
      "meaning": {
        "score": 0.0,
        "flags": [
          "very_short",
          "low_alpha",
          "high_digit",
          "likely_noise"
        ]
      },
      "selection": {
        "selected": false,
        "policy": "threshold"
      },
      "chunk_quality": "noisy"
    },
    {
      "para_id": "p1",
      "section_id": "s2",
      "section_path": [
        "Feedback – Digital Fairness Act",
        "About us"
      ],
      "ordinal": 1,
      "text": "Sveriges Annonsörer (eng: Swedish Association of Advertisers) is the industry association for Swedish advertisers and was founded in 1924. Sveriges Annonsörer has about 400 member companies/organizations, which together account for more than half of the total advertising and media investments in Sweden. As an interest organization, we support our members in working with responsible and ethical marketing that creates value for their brands. Sveriges Annonsörer is a member of the World Federation of Advertisers (WFA).",
      "char_len": 521,
      "chunk_word_count": 79,
      "ratios": {
        "alpha": 0.9574944071588367,
        "digit": 0.015659955257270694,
        "non_space": 0.8579654510556622
      },
      "meaning": {
        "score": 0.9681208053691276,
        "flags": []
      },
      "selection": {
        "selected": true,
        "policy": "threshold+top_k"
      },
      "chunk_quality": "ok"
    },
    {
      "para_id": "p2",
      "section_id": "s3",
      "section_path": [
        "Feedback – Digital Fairness Act",
        "The scope of the feedback"
      ],
      "ordinal": 2,
      "text": "As the industry association of Swedish advertisers, this feedback will focus primarily on issues relating to marketing. This document supplements the response to the associated survey.",
      "char_len": 184,
      "chunk_word_count": 26,
      "ratios": {
        "alpha": 0.9811320754716981,
        "digit": 0.0,
        "non_space": 0.8641304347826086
      },
      "meaning": {
        "score": 0.6497379454926625,
        "flags": []
      },
      "selection": {
        "selected": true,
        "policy": "threshold+top_k"
      },
      "chunk_quality": "ok"
    },
    {
      "para_id": "p3",
      "section_id": "s4",
      "section_path": [
        "Feedback – Digital Fairness Act",
        "Summary"
      ],
      "ordinal": 3,
      "text": "Marketing, when done responsibly, benefits both consumers and the economy by helping consumers identify relevant products and make informed purchasing decisions. EU policy should therefore value both consumer protection and a well-functioning, competitive market. There is no general legislative gap relating to marketing in a digital environment. On the contrary, many of the practices highlighted are already addressed under the Unfair Commercial Practices Directive (UCPD), Digital Services Act (DSA) and other existing acts. The priority should therefore be effective enforcement, harmonized guidance and improved self-regulation. Additional layers of detailed rules should, as a result, only be introduced if absolutely necessary or clearly beneficial for both consumers and the industry.",
      "char_len": 793,
      "chunk_word_count": 109,
      "ratios": {
        "alpha": 0.9708029197080292,
        "digit": 0.0,
        "non_space": 0.8638083228247163
      },
      "meaning": {
        "score": 0.978102189781022,
        "flags": []
      },
      "selection": {
        "selected": true,
        "policy": "threshold+top_k"
      },
      "chunk_quality": "ok"
    },
    {
      "para_id": "p4",
      "section_id": "s5",
      "section_path": [
        "Feedback – Digital Fairness Act",
        "More legislation is not always the answer"
      ],
      "ordinal": 4,
      "text": "From a consumer protection perspective, problems can for example arise when marketing is unfair or aggressive and leads consumers to make poorly informed decisions. Such shortcomings may stem from unclear boundaries between lawful and unlawful marketing or from unethical actors deliberately disregarding existing rules. To address market shortcomings, the Commission needs an approach based on the root causes, whether they relate to lack of guidance, enforcement, regulation, or self-regulation. In general, we see a need for national enforcement authorities and the Commission to do more, particularly in providing guidance under existing rules.",
      "char_len": 648,
      "chunk_word_count": 92,
      "ratios": {
        "alpha": 0.9766606822262118,
        "digit": 0.0,
        "non_space": 0.8595679012345679
      },
      "meaning": {
        "score": 0.982495511669659,
        "flags": []
      },
      "selection": {
        "selected": true,
        "policy": "threshold+top_k"
      },
      "chunk_quality": "ok"
    },
    {
      "para_id": "p5",
      "section_id": "s6",
      "section_path": [
        "Feedback – Digital Fairness Act",
        "General comments on the highlighted areas in the consultation"
      ],
      "ordinal": 5,
      "text": "A few areas are highlighted as problematic in the consultation. We share the Commission’s view that consumer issues exist in a few of these areas and we share the view that more action has to be taken, both by the industry as well as by the authorities.",
      "char_len": 253,
      "chunk_word_count": 48,
      "ratios": {
        "alpha": 0.9806763285024155,
        "digit": 0.0,
        "non_space": 0.8181818181818182
      },
      "meaning": {
        "score": 0.9855072463768118,
        "flags": []
      },
      "selection": {
        "selected": true,
        "policy": "threshold+top_k"
      },
      "chunk_quality": "ok"
    },
    {
      "para_id": "p6",
      "section_id": "s6",
      "section_path": [
        "Feedback – Digital Fairness Act",
        "General comments on the highlighted areas in the consultation"
      ],
      "ordinal": 6,
      "text": "The industry itself has a key part in improving the ethical level of marketing. Sveriges Annonsörer works, as an example, actively with the self-regulatory body Reklamombudsmannen and with industry and trade associations such as Sveriges Kommunikationsbyråer and IAB Sweden to raise standards in the Swedish influencer market. The key in actually making a difference has been for the relevant industry bodies to collaborate to create common standards and recommendations. The national initiative is related to the EU-broad AdEthics led by the European Advertising Standards Alliance (EASA).",
      "char_len": 590,
      "chunk_word_count": 88,
      "ratios": {
        "alpha": 0.9801980198019802,
        "digit": 0.0,
        "non_space": 0.8559322033898306
      },
      "meaning": {
        "score": 0.9851485148514851,
        "flags": []
      },
      "selection": {
        "selected": true,
        "policy": "threshold+top_k"
      },
      "chunk_quality": "ok"
    },
    {
      "para_id": "p7",
      "section_id": "s6",
      "section_path": [
        "Feedback – Digital Fairness Act",
        "General comments on the highlighted areas in the consultation"
      ],
      "ordinal": 7,
      "text": "The commission has earlier shared the sentiment that it is unclear how existing consumer rules apply in the digital market, resulting in for example dark patterns and misleading influencer marketing. Sveriges Annonsörer does not share the view that the application of existing consumer rules, particularly the UCPD, is unclear or generally insufficient in relation to most of the issues listed in the current consultation. Most practices highlighted can, to a large extent, be addressed under existing law through the general, technology-neutral provisions of the UCPD as well as under other existing acts. The focus should therefore primarily be on more effective enforcement and harmonized guidance to bring further clarity rather than new detailed regulations.",
      "char_len": 763,
      "chunk_word_count": 115,
      "ratios": {
        "alpha": 0.9830769230769231,
        "digit": 0.0,
        "non_space": 0.8519003931847968
      },
      "meaning": {
        "score": 0.9873076923076923,
        "flags": []
      },
      "selection": {
        "selected": true,
        "policy": "threshold+top_k"
      },
      "chunk_quality": "ok"
    },
    {
      "para_id": "p8",
      "section_id": "s7",
      "section_path": [
        "Feedback – Digital Fairness Act",
        "Promote and support self-regulation"
      ],
      "ordinal": 8,
      "text": "We advocate for marketers, and the marketing landscape, to maintain high ethical standards. The challenges marketers face can generally be addressed through self-regulation. Self-regulatory measures are often a simpler, cheaper, and faster solution than rigid and reactive legislation. We therefore believe that high ethical standards are often better achieved through self-regulation rather than through legislation. All actors, including the European Commission, should act in a way that supports self-regulation and work towards improving, expanding, and supporting self-regulation. We would like to particularly highlight the updated ICC Code by the International Chamber of Commerce that provides concrete global standards on influencer marketing, environmental claims and communications to children and teens. We encourage the Commission to recognize and support self-regulation wherever possible. It is important that the industry, together with the Commission and national authorities, foster a culture of self-regulation to proactively set high ethical standards in marketing without the need for crisis-driven, reactive legislation.",
      "char_len": 1142,
      "chunk_word_count": 153,
      "ratios": {
        "alpha": 0.9717171717171718,
        "digit": 0.0,
        "non_space": 0.8669001751313485
      },
      "meaning": {
        "score": 0.9787878787878789,
        "flags": []
      },
      "selection": {
        "selected": true,
        "policy": "threshold+top_k"
      },
      "chunk_quality": "ok"
    },
    {
      "para_id": "p9",
      "section_id": "s8",
      "section_path": [
        "Feedback – Digital Fairness Act",
        "When additional legislation may be warranted"
      ],
      "ordinal": 9,
      "text": "Additional legislation can be necessary and warranted, but that should only be the case in situations where existing rules are insufficient despite effective enforcement and clear well-communicated guidance and where self-regulation hasn't had sufficient impact. In other words, where the fundamental issue lies with the legislation. In a large number of cases however, we believe that the shortcomings are not due to legislative gaps but as a lack of clear and well-communicated guidance, enforcement or self-regulation.",
      "char_len": 521,
      "chunk_word_count": 76,
      "ratios": {
        "alpha": 0.9730941704035875,
        "digit": 0.0,
        "non_space": 0.8560460652591171
      },
      "meaning": {
        "score": 0.9798206278026906,
        "flags": []
      },
      "selection": {
        "selected": true,
        "policy": "threshold+top_k"
      },
      "chunk_quality": "ok"
    },
    {
      "para_id": "p10",
      "section_id": "s9",
      "section_path": [
        "Utilize existing rules"
      ],
      "ordinal": 10,
      "text": "In cases where there are existing rules, we see a need for authorities, including the EU-commission, to utilize the current existing rules in a way that does them justice. For example, the consultation implies that the rules on influencer marketing are lacking when it comes to transparency. We question whether such a statement is justified in situations where there has been zero or very few cases tried in the EU-court and where there is still room for clarity through the development of case law and through other guidance. In some cases, you could say that the Commission compensates for a lack of sufficient enforcement and clear guidance, normally provided through case law and guidance by the authorities, by instead proposing additional detailed rules. The lack of solid development of clarifying case law and sufficient guidance has the effect that both current and future legislation will be characterized by legal uncertainty. This also harms the harmonization within the union since case law from the EU-court, together with sound guidance from the Commission, is essential for a clear and similar interpretation among actors in different members states.",
      "char_len": 1167,
      "chunk_word_count": 185,
      "ratios": {
        "alpha": 0.9816887080366226,
        "digit": 0.0,
        "non_space": 0.8423307626392459
      },
      "meaning": {
        "score": 0.986266531027467,
        "flags": []
      },
      "selection": {
        "selected": true,
        "policy": "threshold+top_k"
      },
      "chunk_quality": "ok"
    },
    {
      "para_id": "p11",
      "section_id": "s10",
      "section_path": [
        "Simplifications and the need to avoid overlapping and fragmented rules"
      ],
      "ordinal": 11,
      "text": "Today's regulatory framework for marketers is complex and places tough requirements on those who do their best to comply with the rules. It is therefore of utmost importance that rules are designed with simplicity in mind. To give an example, anyone working with influencer marketing within the EU must navigate three separate regulatory frameworks to determine how to disclose advertising (DSA, UCPD &amp; AVMSD). We advocate for less fragmented and overlapping regulation and see great value in rules that are technology neutral in nature, clear and principle based, making them relevant not only for today's advertising landscape but also for tomorrows. Those qualities can be found in the general provisions in the UCPD.",
      "char_len": 724,
      "chunk_word_count": 113,
      "ratios": {
        "alpha": 0.9754901960784313,
        "digit": 0.0,
        "non_space": 0.8453038674033149
      },
      "meaning": {
        "score": 0.9816176470588236,
        "flags": []
      },
      "selection": {
        "selected": true,
        "policy": "threshold+top_k"
      },
      "chunk_quality": "ok"
    },
    {
      "para_id": "p12",
      "section_id": "s11",
      "section_path": [
        "Requirements must align with the needs of the average consumer"
      ],
      "ordinal": 12,
      "text": "Requirements that stem from legislation must be designed with a clear purpose in mind and thus designed to achieve the intended effect. In recent years, we have observed a trend towards an increase in legislation that mandates certain information in marketing. In our view, this is an example of legislation that might be designed with the consumer in mind, but that risks missing the mark. Information obligations that extend beyond what is essential for the consumer risk overwhelming the consumer with excessive information, thereby diverting attention from what is important for the consumers when making, for instance, a transactional decision. As an example, what value does a three-sentence legal disclosure in an advertisement have if its length causes the consumer to disregard it entirely due to its scope. Add that today's media and advertising landscape increasingly favors fast-moving, short-format content on for example social media, where consumers often scroll quickly and don't take their time to read lengthy informational texts.",
      "char_len": 1048,
      "chunk_word_count": 160,
      "ratios": {
        "alpha": 0.9775028121484814,
        "digit": 0.0,
        "non_space": 0.8482824427480916
      },
      "meaning": {
        "score": 0.9831271091113611,
        "flags": []
      },
      "selection": {
        "selected": true,
        "policy": "threshold+top_k"
      },
      "chunk_quality": "ok"
    },
    {
      "para_id": "p13",
      "section_id": "s11",
      "section_path": [
        "Requirements must align with the needs of the average consumer"
      ],
      "ordinal": 13,
      "text": "Above is an example of where regulation may have legitimate underlying purposes, but where the requirements imposed do not result in benefits in practice for either the average consumer or the marketer due to the design of the rules. The design needs to be proportional and fit for purpose, taking both the consumer and the industry into account.",
      "char_len": 346,
      "chunk_word_count": 58,
      "ratios": {
        "alpha": 0.986159169550173,
        "digit": 0.0,
        "non_space": 0.8352601156069365
      },
      "meaning": {
        "score": 0.9896193771626298,
        "flags": []
      },
      "selection": {
        "selected": true,
        "policy": "threshold+top_k"
      },
      "chunk_quality": "ok"
    },
    {
      "para_id": "p14",
      "section_id": "s11",
      "section_path": [
        "Requirements must align with the needs of the average consumer"
      ],
      "ordinal": 14,
      "text": "Against this background, we identify a few shortcomings in the Commissions proposed measures where the rules are not proportional or fit for purpose. One such example is found within the category \"Horizontal issues\". For instance, the requirement that traders should operate according to \"fairness by design\" raises concerns. We strongly question whether the Commission should dictate operational methods when the only relevant fact is whether the consumer-facing outcome complies with consumer protection laws. Proposals of this nature contribute to excessive regulation of how businesses should operate on a daily basis and should be avoided. This is a clear example of proposals targeting how businesses operate, regardless of whether they act unethically or not, rather than addressing actual negative consumer outcomes. The same reasoning applies to other proposals in the consultation, for example the category \"Unfair marketing related to pricing\". If pricing is misleading, it is already in breach of existing EU legislation. Therefore, regulating the type of pricing strategies that may be used, despite misleading pricing already being prohibited, amounts to prohibiting potentially ethical business models in a way that is neither appropriate, proportional or effective. The focus of marketers should be to create responsible and ethical advertising that creates effect for the marketer and to the benefit of the consumer, it should not be to figure out and implement complex unproportional, or even unnecessary, rules where this is no substantial benefit to the consumer.",
      "char_len": 1583,
      "chunk_word_count": 235,
      "ratios": {
        "alpha": 0.977761304670126,
        "digit": 0.0,
        "non_space": 0.852179406190777
      },
      "meaning": {
        "score": 0.9833209785025945,
        "flags": []
      },
      "selection": {
        "selected": true,
        "policy": "threshold+top_k"
      },
      "chunk_quality": "ok"
    },
    {
      "para_id": "p15",
      "section_id": "s12",
      "section_path": [
        "Requirements must align with the needs of the average consumer",
        "Legislation must not be more burdensome than necessary"
      ],
      "ordinal": 15,
      "text": "New proposals should start with clearly identified problems and be assessed against consumer protection and market efficiency. We note a trend towards detailed and administratively burdensome rules (e.g. certain approaches under the Green Claims initiative). Where equal or better outcomes can be achieved through less burdensome means, enhanced enforcement, guidance, or self-regulation, that route should be preferred. We urge the Commission to systematically assess costs, consequences in practice and cumulative burden on marketers and to prioritize less burdensome and restrictive methods. There are also the risk that new, administratively burdensome rules fall primarily on the vast majority of operators who seek to comply, while the small minority of unethical actors the rules are intended to address may continue to ignore them. The result is a distorted level playing field in where responsible businesses face higher compliance costs and reduced competitiveness, whereas unethical non-compliant actors still dismiss the rules due to a lack of enforcement. The Commission needs to carefully consider how to best tackle bad actors without having unwanted consequences for those who behave well and comply with existing rules. One thing is clear, unnecessarily burdensome rules is not the way forward.",
      "char_len": 1311,
      "chunk_word_count": 193,
      "ratios": {
        "alpha": 0.9794642857142857,
        "digit": 0.0,
        "non_space": 0.8543096872616324
      },
      "meaning": {
        "score": 0.9845982142857144,
        "flags": []
      },
      "selection": {
        "selected": true,
        "policy": "threshold+top_k"
      },
      "chunk_quality": "ok"
    },
    {
      "para_id": "p16",
      "section_id": "s13",
      "section_path": [
        "A final comment on the consultation"
      ],
      "ordinal": 16,
      "text": "Finally, we would like to take the chance to highlight some difficulties that we have had with the structure and the questions in the consultation questionnaire which, in our view, can lead to the survey giving misleading answers. The questions in the survey risk leading the respondent in a way that makes it difficult to see how it is possible to draw well-founded conclusions from the survey results. For example, if you select “no actions are needed” on the introductory questions for each category of questions, you lose the chance to elaborate on your answer. You gain that opportunity, but no chance to elaborate in free text, if you select that actions are needed and in such case a list of suggestions for unethical business practices are shown and you are asked to select the practices which you consider in need of new EU action. You also have the opportunity to select “other” in this second question. The second question is not mandatory and can thus be skipped, but the structure of the questionnaire will certainly get people to click on several of the options proposed by the Commission, even though these respondents would likely never have given notice of these practices without first being directed to them by the Commission. These practices may very well be occurring issues, but the way the survey is structured may result in them being viewed as larger issues for the respondents than what might be fair to conclude. There is, as stated above, also no option or requirement to elaborate in free text on the initial answer on the need for new action and the survey will therefore include no reasoning on why there is, for example, a need for new legislation or more guidance. The answers are therefore unfortunately very unfounded in the survey, regardless of whether there are good arguments for them or not. In summary, the survey, as designed, does unfortunately not provide a good basis on which to base legislation or other measures.",
      "char_len": 1960,
      "chunk_word_count": 334,
      "ratios": {
        "alpha": 0.9797172710510141,
        "digit": 0.0,
        "non_space": 0.8301020408163265
      },
      "meaning": {
        "score": 0.9847879532882606,
        "flags": []
      },
      "selection": {
        "selected": true,
        "policy": "threshold+top_k"
      },
      "chunk_quality": "ok"
    },
    {
      "para_id": "p17",
      "section_id": "s13",
      "section_path": [
        "A final comment on the consultation"
      ],
      "ordinal": 17,
      "text": "Stockholm, 23rd of October 2025",
      "char_len": 31,
      "chunk_word_count": 5,
      "ratios": {
        "alpha": 0.7407407407407407,
        "digit": 0.2222222222222222,
        "non_space": 0.8709677419354839
      },
      "meaning": {
        "score": 0.24,
        "flags": [
          "very_short"
        ]
      },
      "selection": {
        "selected": true,
        "policy": "top_k"
      },
      "chunk_quality": "ok"
    },
    {
      "para_id": "p18",
      "section_id": "s13",
      "section_path": [
        "A final comment on the consultation"
      ],
      "ordinal": 18,
      "text": "Hanna Riberdahl CEO",
      "char_len": 19,
      "chunk_word_count": 3,
      "ratios": {
        "alpha": 1.0,
        "digit": 0.0,
        "non_space": 0.8947368421052632
      },
      "meaning": {
        "score": 0.45,
        "flags": [
          "very_short"
        ]
      },
      "selection": {
        "selected": true,
        "policy": "top_k"
      },
      "chunk_quality": "ok"
    },
    {
      "para_id": "p19",
      "section_id": "s13",
      "section_path": [
        "A final comment on the consultation"
      ],
      "ordinal": 19,
      "text": "Ulrika Wendt Lawyer",
      "char_len": 19,
      "chunk_word_count": 3,
      "ratios": {
        "alpha": 1.0,
        "digit": 0.0,
        "non_space": 0.8947368421052632
      },
      "meaning": {
        "score": 0.45,
        "flags": [
          "very_short"
        ]
      },
      "selection": {
        "selected": true,
        "policy": "top_k"
      },
      "chunk_quality": "ok"
    },
    {
      "para_id": "p20",
      "section_id": "s13",
      "section_path": [
        "A final comment on the consultation"
      ],
      "ordinal": 20,
      "text": "Jakob Rönnerbäck Lawyer",
      "char_len": 23,
      "chunk_word_count": 5,
      "ratios": {
        "alpha": 1.0,
        "digit": 0.0,
        "non_space": 0.9130434782608695
      },
      "meaning": {
        "score": 0.45,
        "flags": [
          "very_short"
        ]
      },
      "selection": {
        "selected": true,
        "policy": "top_k"
      },
      "chunk_quality": "ok"
    }
  ],
  "stats": {
    "sections": 14,
    "paragraphs": 21,
    "selected_paragraphs": 20,
    "selected_ratio": 0.9523809523809523,
    "counts_by_flag": {
      "very_short": 5,
      "low_alpha": 1,
      "high_digit": 1,
      "likely_noise": 1
    }
  }
}