{
  "created_at": "2026-04-01T21:54:23.807278Z",
  "doc_id": "F3618269",
  "feedback": [
    {
      "para_id": "feedback",
      "text": "Companies ought not to have a say on device usage after first sale. Google's actions on mandating identification before running any code is further locking down the mobile market. In the other side of this duopoly, apple has almost maliciously denied applications on the altstore. Me as a citizen must adhere to arbitrary rules that are subject to change from both of these companies with no alternative. This is further enforced by 2 technologies * Bootloader locking * Software attestation Both limit the device features on the android ecosystem if you ran your own software. One is locking the device from running my own OS and the other is punishment for doing it anyways. Something as trivial as the macdonald's app is checking my device for signs of alternative software to deny me usage of the application. Moreover google is actively scanning my device for software installed from outside their marketplace and removing it through play protect.",
      "chunk_quality": "ok"
    }
  ]
}